Workbook
Name AP: Master!$B$16
Name AR: Master!$B$8
Name Capex: Master!$F$10
Name Cash_Bank: Master!$B$6
Name CFO: Master!$F$6
Name COGS: Master!$F$14
Name Dividends: Master!$F$22
Name EBIT: Master!$F$17
Name Gross_Profit: Master!$F$15
Name Interest_Expense: Master!$F$18
Name Inventory: Master!$B$9
Name LT_Debt: Master!$B$20
Name Market_Price: Master!$B$29
Name Net_Profit: Master!$F$21
Name Net_Sales: Master!$F$13
Name Shares_Out: Master!$B$28
Name ST_Investments: Master!$B$7
Name Total_Assets: Master!$B$15
Name Total_Current_Assets: Master!$B$11
Name Total_Current_Liabilities: Master!$B$19
Name Total_Equity: Master!$B$26
Name Total_Liabilities: Master!$B$23

Sheet Dashboard
A1: FINANCIAL RATIO DASHBOARD
A3: Company | B3: =Master!B2 -> Sample Company Ltd | E3: Currency | F3: =Master!E2 -> USD
A4: Period | B4: =Master!B3 -> FY202X
A6: Category | B6: Good | C6: Average | D6: Weak | E6: Total ratios | F6: Category verdict | G6: %Scored (Good Cat)
A7: Liquidity | B7: =COUNTIF(Liquidity!E4:E6,"Good") -> 2 | C7: =COUNTIF(Liquidity!E4:E6,"Average") -> 1 | D7: =COUNTIF(Liquidity!E4:E6,"Weak") -> 0 | E7: =B7+C7+D7 -> 3 | F7: =IF(B7/E7>=0.6,"Strong",IF((B7+C7)/E7>=0.6,"Moderate - mixed signals","Weak - needs attention")) -> Strong | G7: =B7/E7 -> 0.66666667
A8: Profitability | B8: =COUNTIF(Profitability!E4:E8,"Good") -> 5 | C8: =COUNTIF(Profitability!E4:E8,"Average") -> 0 | D8: =COUNTIF(Profitability!E4:E8,"Weak") -> 0 | E8: =B8+C8+D8 -> 5 | F8: =IF(B8/E8>=0.6,"Strong",IF((B8+C8)/E8>=0.6,"Moderate - mixed signals","Weak - needs attention")) -> Strong | G8: =B8/E8 -> 1
A9: Efficiency | B9: =COUNTIF(Efficiency!E4:E8,"Good") -> 1 | C9: =COUNTIF(Efficiency!E4:E8,"Average") -> 4 | D9: =COUNTIF(Efficiency!E4:E8,"Weak") -> 0 | E9: =B9+C9+D9 -> 5 | F9: =IF(B9/E9>=0.6,"Strong",IF((B9+C9)/E9>=0.6,"Moderate - mixed signals","Weak - needs attention")) -> Moderate - mixed signals | G9: =B9/E9 -> 0.2
A10: Leverage | B10: =COUNTIF(Leverage!E4:E7,"Good") -> 3 | C10: =COUNTIF(Leverage!E4:E7,"Average") -> 1 | D10: =COUNTIF(Leverage!E4:E7,"Weak") -> 0 | E10: =B10+C10+D10 -> 4 | F10: =IF(B10/E10>=0.6,"Strong",IF((B10+C10)/E10>=0.6,"Moderate - mixed signals","Weak - needs attention")) -> Strong | G10: =B10/E10 -> 0.75
A11: Investor (scored) | B11: =COUNTIF(Investor!E6,"Good")+COUNTIF(Investor!E8,"Good") -> 2 | C11: =COUNTIF(Investor!E6,"Average")+COUNTIF(Investor!E8,"Average") -> 0 | D11: =COUNTIF(Investor!E6,"Weak")+COUNTIF(Investor!E8,"Weak") -> 0 | E11: =B11+C11+D11 -> 2 | F11: =IF(B11/E11>=0.6,"Strong",IF((B11+C11)/E11>=0.6,"Moderate - mixed signals","Weak - needs attention")) -> Strong | G11: =B11/E11 -> 1
A12: TOTAL | B12: =SUM(B7:B11) -> 13 | C12: =SUM(C7:C11) -> 6 | D12: =SUM(D7:D11) -> 0 | E12: =SUM(E7:E11) -> 19

Sheet Master
A1: MASTER INPUT SHEET
A2: Company Name | B2: Sample Company Ltd | D2: Currency | E2: USD
A3: Period | B3: FY202X
A5: BALANCE SHEET | B5: Amount | E5: CASH FLOW STATEMENT | F5: Amount
A6: Cash & Bank | B6: 45000 | E6: Cash Flow from Operations (CFO) | F6: 95000
A7: Short-term Investments | B7: 15000 | E7: Cash Flow from Investing (CFI) | F7: -40000
A8: Accounts Receivable (Trade Debts) | B8: 120000 | E8: Cash Flow from Financing (CFF) | F8: -20000
A9: Inventory (Stock-in-Trade) | B9: 180000 | E9: Net Change in Cash | F9: =SUM(F6:F8) -> 35000
A10: Other Current Assets | B10: 10000 | E10: Capital Expenditure (Capex) | F10: 40000
A11: Total Current Assets | B11: =SUM(B6:B10) -> 370000
A12: Net Fixed Assets (PP&E) | B12: 320000 | E12: INCOME STATEMENT | F12: Amount
A13: Other Non-Current Assets | B13: 20000 | E13: Net Sales / Revenue | F13: 900000
A14: Total Non-Current Assets | B14: =SUM(B12:B13) -> 340000 | E14: Cost of Goods Sold (COGS) | F14: 630000
A15: Total Assets | B15: =B11+B14 -> 710000 | E15: Gross Profit | F15: =F13-F14 -> 270000
A16: Accounts Payable (Trade Creditors) | B16: 90000 | E16: Operating Expenses | F16: 130000
A17: Short-term Borrowings | B17: 60000 | E17: EBIT (Operating Profit) | F17: =F15-F16 -> 140000
A18: Other Current Liabilities | B18: 15000 | E18: Interest Expense | F18: 25000
A19: Total Current Liabilities | B19: =SUM(B16:B18) -> 165000 | E19: Profit Before Tax | F19: =F17-F18 -> 115000
A20: Long-term Debt | B20: 130000 | E20: Tax | F20: 20000
A21: Other Non-Current Liabilities | B21: 10000 | E21: Net Profit | F21: =F19-F20 -> 95000
A22: Total Non-Current Liabilities | B22: =SUM(B20:B21) -> 140000 | E22: Dividends Paid | F22: 30000
A23: Total Liabilities | B23: =B19+B22 -> 305000
A24: Share Capital | B24: 100000
A25: Reserves & Retained Earnings | B25: 200000
A26: Total Equity | B26: =SUM(B24:B25) -> 300000
A27: Total Liabilities & Equity (check) | B27: =B23+B26 -> 605000
A28: Number of Shares Outstanding | B28: 10000
A29: Market Price per Share | B29: 45

Sheet Liquidity
A1: LIQUIDITY RATIOS
A3: Ratio | B3: Formula | C3: Value | D3: Benchmark | E3: Signal
A4: Current Ratio | B4: Total Current Assets / Total Current Liabilities | C4: =Total_Current_Assets/Total_Current_Liabilities -> 2.2424242 | D4: Good >=1.5, Avg >=1.0 | E4: =IF(C4>=1.5,"Good",IF(C4>=1,"Average","Weak")) -> Good
A5: Quick Ratio (Acid Test) | B5: (Current Assets - Inventory) / Current Liabilities | C5: =(Total_Current_Assets-Inventory)/Total_Current_Liabilities -> 1.1515152 | D5: Good >=1.0, Avg >=0.75 | E5: =IF(C5>=1,"Good",IF(C5>=0.75,"Average","Weak")) -> Good
A6: Cash Ratio | B6: (Cash + Short-term Investments) / Current Liabilities | C6: =(Cash_Bank+ST_Investments)/Total_Current_Liabilities -> 0.36363636 | D6: Good >=0.5, Avg >=0.2 | E6: =IF(C6>=0.5,"Good",IF(C6>=0.2,"Average","Weak")) -> Average

Sheet Profitability
A1: PROFITABILITY RATIOS
A3: Ratio | B3: Formula | C3: Value | D3: Benchmark | E3: Signal
A4: Gross Profit Margin | B4: Gross Profit / Net Sales | C4: =Gross_Profit/Net_Sales -> 0.3 | D4: Good >=30%, Avg >=15% | E4: =IF(C4>=0.3,"Good",IF(C4>=0.15,"Average","Weak")) -> Good
A5: Net Profit Margin | B5: Net Profit / Net Sales | C5: =Net_Profit/Net_Sales -> 0.10555556 | D5: Good >=10%, Avg >=5% | E5: =IF(C5>=0.1,"Good",IF(C5>=0.05,"Average","Weak")) -> Good
A6: Operating Margin | B6: EBIT / Net Sales | C6: =EBIT/Net_Sales -> 0.15555556 | D6: Good >=15%, Avg >=8% | E6: =IF(C6>=0.15,"Good",IF(C6>=0.08,"Average","Weak")) -> Good
A7: Return on Assets (ROA) | B7: Net Profit / Total Assets | C7: =Net_Profit/Total_Assets -> 0.13380282 | D7: Good >=8%, Avg >=4% | E7: =IF(C7>=0.08,"Good",IF(C7>=0.04,"Average","Weak")) -> Good
A8: Return on Equity (ROE) | B8: Net Profit / Total Equity | C8: =Net_Profit/Total_Equity -> 0.31666667 | D8: Good >=15%, Avg >=8% | E8: =IF(C8>=0.15,"Good",IF(C8>=0.08,"Average","Weak")) -> Good

Sheet Efficiency
A1: EFFICIENCY RATIOS
A3: Ratio | B3: Formula | C3: Value | D3: Benchmark | E3: Signal
A4: Inventory Turnover | B4: COGS / Inventory | C4: =COGS/Inventory -> 3.5 | D4: Good >=6x, Avg >=3x | E4: =IF(C4>=6,"Good",IF(C4>=3,"Average","Weak")) -> Average
A5: Days Inventory Outstanding | B5: 365 / Inventory Turnover | C5: =365/(COGS/Inventory) -> 104.28571 | D5: Good <=60d, Avg <=120d | E5: =IF(C5<=60,"Good",IF(C5<=120,"Average","Weak")) -> Average
A6: Receivables Turnover | B6: Net Sales / Accounts Receivable | C6: =Net_Sales/AR -> 7.5 | D6: Good >=8x, Avg >=4x | E6: =IF(C6>=8,"Good",IF(C6>=4,"Average","Weak")) -> Average
A7: Days Sales Outstanding (DSO) | B7: 365 / Receivables Turnover | C7: =365/(Net_Sales/AR) -> 48.666667 | D7: Good <=45d, Avg <=90d | E7: =IF(C7<=45,"Good",IF(C7<=90,"Average","Weak")) -> Average
A8: Asset Turnover | B8: Net Sales / Total Assets | C8: =Net_Sales/Total_Assets -> 1.2676056 | D8: Good >=1.0x, Avg >=0.5x | E8: =IF(C8>=1,"Good",IF(C8>=0.5,"Average","Weak")) -> Good

Sheet Leverage
A1: LEVERAGE RATIOS
A3: Ratio | B3: Formula | C3: Value | D3: Benchmark | E3: Signal
A4: Debt to Equity | B4: Total Liabilities / Total Equity | C4: =Total_Liabilities/Total_Equity -> 1.0166667 | D4: Good <=1.0, Avg <=2.0 | E4: =IF(C4<=1,"Good",IF(C4<=2,"Average","Weak")) -> Average
A5: Debt to Assets | B5: Total Liabilities / Total Assets | C5: =Total_Liabilities/Total_Assets -> 0.42957746 | D5: Good <=50%, Avg <=65% | E5: =IF(C5<=0.5,"Good",IF(C5<=0.65,"Average","Weak")) -> Good
A6: Interest Coverage Ratio (ICR) | B6: EBIT / Interest Expense | C6: =EBIT/Interest_Expense -> 5.6 | D6: Good >=5x, Avg >=2.5x | E6: =IF(C6>=5,"Good",IF(C6>=2.5,"Average","Weak")) -> Good
A7: Long-term Debt to Equity | B7: Long-term Debt / Total Equity | C7: =LT_Debt/Total_Equity -> 0.43333333 | D7: Good <=0.5, Avg <=1.0 | E7: =IF(C7<=0.5,"Good",IF(C7<=1,"Average","Weak")) -> Good

Sheet Investor
A1: INVESTOR RATIOS
A3: Ratio | B3: Formula | C3: Value | D3: Benchmark | E3: Signal
A4: Earnings Per Share (EPS) | B4: Net Profit / Shares Outstanding | C4: =Net_Profit/Shares_Out -> 9.5 | D4: Informational | E4: =IF(C4>0,"Info - Positive","Info - Negative") -> Info - Positive
A5: Price to Earnings (P/E) | B5: Market Price / EPS | C5: =Market_Price/(Net_Profit/Shares_Out) -> 4.7368421 | D5: 8-20x typically reasonable | E5: =IF(C5<8,"Info - Possibly undervalued",IF(C5<=20,"Info - Reasonable range","Info - Possibly overvalued")) -> Info - Possibly undervalued
A6: Dividend Yield | B6: (Dividends / Shares Outstanding) / Market Price | C6: =(Dividends/Shares_Out)/Market_Price -> 0.066666667 | D6: Good >=5%, Avg >=2% | E6: =IF(C6>=0.05,"Good",IF(C6>=0.02,"Average","Weak")) -> Good
A7: Book Value per Share | B7: Total Equity / Shares Outstanding | C7: =Total_Equity/Shares_Out -> 30 | D7: Informational | E7: =""
A8: Dividend Payout Ratio | B8: Dividends Paid / Net Profit | C8: =Dividends/Net_Profit -> 0.31578947 | D8: Good 30-60% balanced | E8: =IF(AND(C8>=0.3,C8<=0.6),"Good",IF(C8<0.3,"Average","Average")) -> Good
